
main <__add.lua:0,0> (31 instructions at 0x55e5f580dc70)
0+ params, 8 slots, 1 upvalue, 4 locals, 13 constants, 4 functions
	1	[1]	NEWTABLE 	0 0 0
	2	[7]	CLOSURE  	1 0	; 0x55e5f580dee0
	3	[7]	SETTABLE 	0 -1 1	; "__add" -
	4	[9]	NEWTABLE 	1 0 1
	5	[9]	SETTABLE 	1 -2 -3	; "v" 10
	6	[10]	NEWTABLE 	2 0 1
	7	[10]	SETTABLE 	2 -2 -4	; "v" 12
	8	[12]	GETTABUP 	3 0 -5	; _ENV "setmetatable"
	9	[12]	MOVE     	4 1
	10	[12]	MOVE     	5 0
	11	[12]	CALL     	3 3 1
	12	[19]	CLOSURE  	3 1	; 0x55e5f580ec30
	13	[14]	SETTABUP 	0 -6 3	; _ENV "traceback"
	14	[24]	CLOSURE  	3 2	; 0x55e5f580f050
	15	[27]	GETTABUP 	4 0 -8	; _ENV "coroutine"
	16	[27]	GETTABLE 	4 4 -9	; "create"
	17	[31]	CLOSURE  	5 3	; 0x55e5f580f2e0
	18	[27]	CALL     	4 2 2
	19	[31]	SETTABUP 	0 -7 4	; _ENV "coco"
	20	[32]	GETTABUP 	4 0 -8	; _ENV "coroutine"
	21	[32]	GETTABLE 	4 4 -10	; "resume"
	22	[32]	GETTABUP 	5 0 -7	; _ENV "coco"
	23	[32]	LOADK    	6 -11	; 0
	24	[32]	LOADK    	7 -12	; 1
	25	[32]	CALL     	4 4 1
	26	[33]	GETTABUP 	4 0 -8	; _ENV "coroutine"
	27	[33]	GETTABLE 	4 4 -10	; "resume"
	28	[33]	GETTABUP 	5 0 -7	; _ENV "coco"
	29	[33]	LOADK    	6 -13	; 21
	30	[33]	CALL     	4 3 1
	31	[33]	RETURN   	0 1
constants (13) for 0x55e5f580dc70:
	1	"__add"
	2	"v"
	3	10
	4	12
	5	"setmetatable"
	6	"traceback"
	7	"coco"
	8	"coroutine"
	9	"create"
	10	"resume"
	11	0
	12	1
	13	21
locals (4) for 0x55e5f580dc70:
	0	mt	2	32
	1	a	6	32
	2	b	8	32
	3	main	15	32
upvalues (1) for 0x55e5f580dc70:
	0	_ENV	1	0

function <__add.lua:3,7> (12 instructions at 0x55e5f580dee0)
2 params, 4 slots, 1 upvalue, 2 locals, 6 constants, 0 functions
	1	[4]	GETTABUP 	2 0 -1	; _ENV "coroutine"
	2	[4]	GETTABLE 	2 2 -2	; "yield"
	3	[4]	CALL     	2 1 1
	4	[5]	GETTABUP 	2 0 -3	; _ENV "print"
	5	[5]	LOADK    	3 -4	; "yield resume"
	6	[5]	CALL     	2 2 1
	7	[6]	GETTABLE 	2 0 -5	; "v"
	8	[6]	GETTABLE 	3 1 -5	; "v"
	9	[6]	DIV      	3 3 -6	; - 2
	10	[6]	ADD      	2 2 3
	11	[6]	RETURN   	2 2
	12	[7]	RETURN   	0 1
constants (6) for 0x55e5f580dee0:
	1	"coroutine"
	2	"yield"
	3	"print"
	4	"yield resume"
	5	"v"
	6	2
locals (2) for 0x55e5f580dee0:
	0	a	1	13
	1	b	1	13
upvalues (1) for 0x55e5f580dee0:
	0	_ENV	0	0

function <__add.lua:14,19> (20 instructions at 0x55e5f580ec30)
1 param, 5 slots, 1 upvalue, 1 local, 7 constants, 0 functions
	1	[15]	GETTABUP 	1 0 -1	; _ENV "print"
	2	[15]	LOADK    	2 -2	; "----------------------------------------"
	3	[15]	CALL     	1 2 1
	4	[16]	GETTABUP 	1 0 -1	; _ENV "print"
	5	[16]	LOADK    	2 -3	; "LUA ERROR: "
	6	[16]	GETTABUP 	3 0 -4	; _ENV "tostring"
	7	[16]	MOVE     	4 0
	8	[16]	CALL     	3 2 2
	9	[16]	LOADK    	4 -5	; "\n"
	10	[16]	CONCAT   	2 2 4
	11	[16]	CALL     	1 2 1
	12	[17]	GETTABUP 	1 0 -1	; _ENV "print"
	13	[17]	GETTABUP 	2 0 -6	; _ENV "debug"
	14	[17]	GETTABLE 	2 2 -7	; "traceback"
	15	[17]	CALL     	2 1 0
	16	[17]	CALL     	1 0 1
	17	[18]	GETTABUP 	1 0 -1	; _ENV "print"
	18	[18]	LOADK    	2 -2	; "----------------------------------------"
	19	[18]	CALL     	1 2 1
	20	[19]	RETURN   	0 1
constants (7) for 0x55e5f580ec30:
	1	"print"
	2	"----------------------------------------"
	3	"LUA ERROR: "
	4	"tostring"
	5	"\n"
	6	"debug"
	7	"traceback"
locals (1) for 0x55e5f580ec30:
	0	msg	1	21
upvalues (1) for 0x55e5f580ec30:
	0	_ENV	0	0

function <__add.lua:21,24> (10 instructions at 0x55e5f580f050)
0 params, 4 slots, 3 upvalues, 0 locals, 3 constants, 0 functions
	1	[22]	GETTABUP 	0 0 -1	; _ENV "print"
	2	[22]	LOADK    	1 -2	; "hello"
	3	[22]	CALL     	0 2 1
	4	[23]	GETTABUP 	0 0 -1	; _ENV "print"
	5	[23]	LOADK    	1 -3	; "a + b :"
	6	[23]	GETUPVAL 	2 1	; a
	7	[23]	GETUPVAL 	3 2	; b
	8	[23]	ADD      	2 2 3
	9	[23]	CALL     	0 3 1
	10	[24]	RETURN   	0 1
constants (3) for 0x55e5f580f050:
	1	"print"
	2	"hello"
	3	"a + b :"
locals (0) for 0x55e5f580f050:
upvalues (3) for 0x55e5f580f050:
	0	_ENV	0	0
	1	a	1	1
	2	b	1	2

function <__add.lua:27,31> (20 instructions at 0x55e5f580f2e0)
2 params, 7 slots, 2 upvalues, 2 locals, 9 constants, 0 functions
	1	[28]	GETTABUP 	2 0 -1	; _ENV "print"
	2	[28]	LOADK    	3 -2	; "resume args:"
	3	[28]	MOVE     	4 0
	4	[28]	LOADK    	5 -3	; ","
	5	[28]	MOVE     	6 1
	6	[28]	CONCAT   	3 3 6
	7	[28]	CALL     	2 2 1
	8	[29]	GETTABUP 	2 0 -6	; _ENV "xpcall"
	9	[29]	GETUPVAL 	3 1	; main
	10	[29]	GETTABUP 	4 0 -7	; _ENV "traceback"
	11	[29]	CALL     	2 3 3
	12	[29]	SETTABUP 	0 -5 3	; _ENV "yr"
	13	[29]	SETTABUP 	0 -4 2	; _ENV "ab"
	14	[30]	GETTABUP 	2 0 -1	; _ENV "print"
	15	[30]	LOADK    	3 -8	; "yreturn and ab:"
	16	[30]	GETTABUP 	4 0 -9	; _ENV "yreturn"
	17	[30]	CONCAT   	3 3 4
	18	[30]	GETTABUP 	4 0 -4	; _ENV "ab"
	19	[30]	CALL     	2 3 1
	20	[31]	RETURN   	0 1
constants (9) for 0x55e5f580f2e0:
	1	"print"
	2	"resume args:"
	3	","
	4	"ab"
	5	"yr"
	6	"xpcall"
	7	"traceback"
	8	"yreturn and ab:"
	9	"yreturn"
locals (2) for 0x55e5f580f2e0:
	0	a	1	21
	1	b	1	21
upvalues (2) for 0x55e5f580f2e0:
	0	_ENV	0	0
	1	main	1	3
