
main <up.lua:0,0> (12 instructions at 0x1308a20)
0+ params, 3 slots, 1 upvalue, 0 locals, 5 constants, 1 function
	1	[5]	CLOSURE  	0 0	; 0x1308bc0
	2	[1]	SETTABUP 	0 -1 0	; _ENV "add"
	3	[7]	GETTABUP 	0 0 -1	; _ENV "add"
	4	[7]	LOADK    	1 -3	; 2
	5	[7]	CALL     	0 2 2
	6	[7]	SETTABUP 	0 -2 0	; _ENV "add2"
	7	[8]	GETTABUP 	0 0 -4	; _ENV "print"
	8	[8]	GETTABUP 	1 0 -2	; _ENV "add2"
	9	[8]	LOADK    	2 -5	; 5
	10	[8]	CALL     	1 2 0
	11	[8]	CALL     	0 0 1
	12	[8]	RETURN   	0 1
constants (5) for 0x1308a20:
	1	"add"
	2	"add2"
	3	2
	4	"print"
	5	5
locals (0) for 0x1308a20:
upvalues (1) for 0x1308a20:
	0	_ENV	1	0

function <up.lua:1,5> (3 instructions at 0x1308bc0)
1 param, 2 slots, 0 upvalues, 1 local, 0 constants, 1 function
	1	[4]	CLOSURE  	1 0	; 0x1308d30
	2	[4]	RETURN   	1 2
	3	[5]	RETURN   	0 1
constants (0) for 0x1308bc0:
locals (1) for 0x1308bc0:
	0	x	1	4
upvalues (0) for 0x1308bc0:

function <up.lua:2,4> (4 instructions at 0x1308d30)
1 param, 2 slots, 1 upvalue, 1 local, 0 constants, 0 functions
	1	[3]	GETUPVAL 	1 0	; x
	2	[3]	ADD      	1 1 0
	3	[3]	RETURN   	1 2
	4	[4]	RETURN   	0 1
constants (0) for 0x1308d30:
locals (1) for 0x1308d30:
	0	y	1	5
upvalues (1) for 0x1308d30:
	0	x	1	0
